Metadata-Version: 2.1
Name: pack-python
Version: 0.1
Summary: Projeto Open Source Python
Home-page: https://github.com/cleysoncassio/Open
Author: Cleyson Cassio
Author-email: cleysoncassio@gmail.com
License: GNU AFFERO GENERAL PUBLIC LICENSE
Platform: UNKNOWN
Classifier: Development Status :: 2 - Pre-Alpha
Classifier: Environment :: Console
Classifier: Intended Audience :: Developers
Classifier: License :: OSI Approved :: GNU Affero General Public License v3 or later (AGPLv3+)
Classifier: Operating System :: OS Independent
Classifier: Programming Language :: Python
Classifier: Programming Language :: Python :: 3.9
Classifier: Framework :: Pytest
